matalg/__init__.py
matrix_alg-0.1.dist-info/LICENCE.txt
matrix_alg-0.1.dist-info/METADATA
matrix_alg-0.1.dist-info/WHEEL
matrix_alg-0.1.dist-info/top_level.txt
matrix_alg-0.1.dist-info/RECORD
