Metadata-Version: 2.1
Name: matrix-alg
Version: 0.1
Summary: Basic matrix algebra
Author: Aditya Panayal
Author-email: adpanayal@gmail.com
Classifier: Programming Language :: Python :: 3
Classifier: License :: OSI Approved :: MIT License
Classifier: Operating System :: OS Independent
License-File: LICENCE.txt
